{
    "Page": {
        "Name": "My Stories",
        "Section": [
            {
                "Name": "Stories",
                "TabBar": {
                    "viewBar": "False",
                    "Edit": {
                        "canEdit": "True",
                        "Type": "Basic"
                    }
                },
                "Type": "Table",
                "Data": {
                    "Identifier": "STORY_ID",
                    "Value": "Headline",
                    "Data": [

                    ]
                }
            }
     
        ]
    }
}